amcp_pylib/__init__.py
amcp_pylib/core/__init__.py
amcp_pylib/core/client.py
amcp_pylib/core/client_async.py
amcp_pylib/core/client_base.py
amcp_pylib/core/command.py
amcp_pylib/core/connection.py
amcp_pylib/core/connection_async.py
amcp_pylib/core/connection_base.py
amcp_pylib/core/syntax/__init__.py
amcp_pylib/core/syntax/command_argument.py
amcp_pylib/core/syntax/command_group.py
amcp_pylib/core/syntax/command_group_or.py
amcp_pylib/core/syntax/parser.py
amcp_pylib/core/syntax/scanner.py
amcp_pylib/core/syntax/token.py
amcp_pylib/core/syntax/token_types.py
amcp_pylib/module/__init__.py
amcp_pylib/module/basic.py
amcp_pylib/module/data.py
amcp_pylib/module/mixer.py
amcp_pylib/module/query.py
amcp_pylib/module/template.py
amcp_pylib/module/thumbnail.py
amcp_pylib/response/__init__.py
amcp_pylib/response/response_base.py
amcp_pylib/response/response_factory.py
amcp_pylib/response/types/__init__.py
amcp_pylib/response/types/client_error_response.py
amcp_pylib/response/types/info_response.py
amcp_pylib/response/types/server_error_response.py
amcp_pylib/response/types/success_response.py
amcp_pylib/tests/__init__.py
amcp_pylib/tests/test_core_syntax_scanner.py
amcp_pylib-0.2.2.dist-info/LICENSE.md
amcp_pylib-0.2.2.dist-info/METADATA
amcp_pylib-0.2.2.dist-info/WHEEL
amcp_pylib-0.2.2.dist-info/top_level.txt
amcp_pylib-0.2.2.dist-info/RECORD
