Metadata-Version: 2.1
Name: amcp-pylib
Version: 0.2.2
Summary: AMCP (Advanced Media Control Protocol) Client Library
Home-page: https://github.com/dolejska-daniel/amcp-pylib
Author: Daniel Dolejska
Author-email: dolejskad@gmail.com
License: MIT
Platform: UNKNOWN
Classifier: Development Status :: 5 - Production/Stable
Classifier: Intended Audience :: Developers
Classifier: License :: OSI Approved :: MIT License
Classifier: Natural Language :: English
Classifier: Operating System :: OS Independent
Classifier: Programming Language :: Python :: 3
Classifier: Topic :: Multimedia :: Video
Classifier: Topic :: Utilities
